{"_ts":[1535578834],"_r":{"breakdown":{"html":{"bytes":[23843],"requests":[5]},"js":{"bytes":[143729],"requests":[9]},"css":{"bytes":[77372],"requests":[5]},"image":{"bytes":[3971117],"requests":[23]},"flash":{"bytes":[0],"requests":[0]},"font":{"bytes":[20045],"requests":[1]},"video":{"bytes":[2734639],"requests":[1]},"other":{"bytes":[0],"requests":[1]}},"date":[1535578834],"domElements":[363],"domInteractive":[4173],"firstPaint":[4322.0000000001],"fullyLoaded":[14853],"id":["180829_G4_668e63801a30183fdceac01704443e7d"],"loadTime":[11134],"render":[5300],"SpeedIndex":[6734],"TTFB":[2372],"videoFrames":[[{"_i":"ms_000000.jpg","_t":0,"_vc":0},{"_i":"ms_005300.jpg","_t":5300,"_vc":71},{"_i":"ms_005500.jpg","_t":5500,"_vc":74},{"_i":"ms_006500.jpg","_t":6500,"_vc":78},{"_i":"ms_006900.jpg","_t":6900,"_vc":78},{"_i":"ms_007100.jpg","_t":7100,"_vc":85},{"_i":"ms_008300.jpg","_t":8300,"_vc":85},{"_i":"ms_008600.jpg","_t":8600,"_vc":85},{"_i":"ms_008900.jpg","_t":8900,"_vc":85},{"_i":"ms_009300.jpg","_t":9300,"_vc":85},{"_i":"ms_009600.jpg","_t":9600,"_vc":85},{"_i":"ms_010000.jpg","_t":10000,"_vc":85},{"_i":"ms_010300.jpg","_t":10300,"_vc":85},{"_i":"ms_010700.jpg","_t":10700,"_vc":85},{"_i":"ms_011000.jpg","_t":11000,"_vc":87},{"_i":"ms_011100.jpg","_t":11100,"_vc":87},{"_i":"ms_011200.jpg","_t":11200,"_vc":87},{"_i":"ms_011300.jpg","_t":11300,"_vc":87},{"_i":"ms_011400.jpg","_t":11400,"_vc":87},{"_i":"ms_011500.jpg","_t":11500,"_vc":87},{"_i":"ms_012000.jpg","_t":12000,"_vc":87},{"_i":"ms_012500.jpg","_t":12500,"_vc":87},{"_i":"ms_013000.jpg","_t":13000,"_vc":87},{"_i":"ms_013500.jpg","_t":13500,"_vc":87},{"_i":"ms_014000.jpg","_t":14000,"_vc":99},{"_i":"ms_014500.jpg","_t":14500,"_vc":99},{"_i":"ms_014900.jpg","_t":14900,"_vc":100}]],"visualComplete":[14900],"lighthouse":[50],"pagespeed":[16]}}